[
  {
    "timestamp": "2025-07-11T06:47:31.041Z",
    "level": "info",
    "message": "No Project Management Extension found, using basic project tracking",
    "sessionId": "session-20250711-024731"
  },
  {
    "timestamp": "2025-07-11T06:47:31.043Z",
    "level": "info",
    "message": "Detected 114 installed extensions",
    "sessionId": "session-20250711-024731"
  },
  {
    "timestamp": "2025-07-11T06:47:31.046Z",
    "level": "info",
    "message": "Detected 114 installed extensions",
    "sessionId": "session-20250711-024731"
  },
  {
    "timestamp": "2025-07-11T06:47:31.048Z",
    "level": "info",
    "message": "Detected 114 installed extensions",
    "sessionId": "session-20250711-024731"
  },
  {
    "timestamp": "2025-07-11T06:47:31.051Z",
    "level": "info",
    "message": "Loaded 34 Cursorrules",
    "sessionId": "session-20250711-024731"
  },
  {
    "timestamp": "2025-07-11T06:47:31.054Z",
    "level": "info",
    "message": "Sprint templates loaded",
    "data": {
      "templateCount": 2
    },
    "sessionId": "session-20250711-024731"
  },
  {
    "timestamp": "2025-07-11T06:47:31.055Z",
    "level": "info",
    "message": "Sprint planner storage initialized",
    "sessionId": "session-20250711-024731"
  },
  {
    "timestamp": "2025-07-11T06:47:31.059Z",
    "level": "info",
    "message": "No Project Management Extension found, using basic project tracking",
    "sessionId": "session-20250711-024731"
  },
  {
    "timestamp": "2025-07-11T06:47:31.063Z",
    "level": "info",
    "message": "No Project Management Extension found, using basic project tracking",
    "sessionId": "session-20250711-024731"
  },
  {
    "timestamp": "2025-07-11T06:47:31.064Z",
    "level": "info",
    "message": "Sprint templates loaded",
    "data": {
      "templateCount": 2
    },
    "sessionId": "session-20250711-024731"
  },
  {
    "timestamp": "2025-07-11T06:47:31.066Z",
    "level": "info",
    "message": "Sprint planner storage initialized",
    "sessionId": "session-20250711-024731"
  }
]